otii_tcp_client/__init__.py
otii_tcp_client/arc.py
otii_tcp_client/battery_emulator.py
otii_tcp_client/otii.py
otii_tcp_client/otii_client.py
otii_tcp_client/otii_connection.py
otii_tcp_client/otii_control.py
otii_tcp_client/otii_exception.py
otii_tcp_client/project.py
otii_tcp_client/recording.py
otii_tcp_client-1.0.11.dist-info/licenses/LICENSE
otii_tcp_client-1.0.11.dist-info/METADATA
otii_tcp_client-1.0.11.dist-info/WHEEL
otii_tcp_client-1.0.11.dist-info/top_level.txt
otii_tcp_client-1.0.11.dist-info/RECORD
