Metadata-Version: 2.4
Name: otii_tcp_client
Version: 1.0.11
Summary: Qoitech Otii tcp client library
Author-email: Qoitech AB <support@qoitech.com>
Project-URL: Homepage, https://github.com/qoitech/otii-tcp-client-python
Classifier: Programming Language :: Python :: 3
Classifier: Operating System :: OS Independent
Classifier: License :: OSI Approved :: MIT License
Classifier: Topic :: Software Development :: Build Tools
Classifier: Development Status :: 5 - Production/Stable
Requires-Python: >=3.9
License-File: LICENSE
Dynamic: license-file
